graphsh/__init__.py
graphsh/__main__.py
graphsh/cli/__init__.py
graphsh/cli/app.py
graphsh/cli/commands.py
graphsh/cli/logger.py
graphsh/cli/repl.py
graphsh/config/__init__.py
graphsh/config/preferences.py
graphsh/config/profiles.py
graphsh/db/__init__.py
graphsh/db/connection.py
graphsh/db/adapters/__init__.py
graphsh/db/adapters/base.py
graphsh/db/adapters/factory.py
graphsh/db/adapters/neo4j.py
graphsh/db/adapters/neptune.py
graphsh/db/adapters/neptune_analytics.py
graphsh/db/adapters/tinkerpop.py
graphsh/db/converters/__init__.py
graphsh/db/converters/base.py
graphsh/db/converters/neo4j.py
graphsh/db/converters/neptune.py
graphsh/db/converters/tinkerpop.py
graphsh/lang/__init__.py
graphsh/lang/base.py
graphsh/lang/cypher.py
graphsh/lang/gremlin.py
graphsh/lang/sparql.py
graphsh/models/__init__.py
graphsh/models/graph.py
graphsh/renderers/__init__.py
graphsh/renderers/base.py
graphsh/renderers/factory.py
graphsh/renderers/raw.py
graphsh/renderers/table.py
graphsh-0.1.1.dist-info/licenses/LICENSE
graphsh-0.1.1.dist-info/licenses/NOTICE
graphsh-0.1.1.dist-info/METADATA
graphsh-0.1.1.dist-info/WHEEL
graphsh-0.1.1.dist-info/entry_points.txt
graphsh-0.1.1.dist-info/top_level.txt
graphsh-0.1.1.dist-info/RECORD
