Metadata-Version: 2.4
Name: graphsh
Version: 0.1.1
Summary: Interactive Terminal Client for Graph Databases
Author-email: amazon-neptune <amazon-neptune-pypi@amazon.com>
Project-URL: Homepage, https://github.com/awslabs/graphsh
Project-URL: Repository, https://github.com/awslabs/graphsh
Classifier: Development Status :: 3 - Alpha
Classifier: Intended Audience :: Developers
Classifier: Programming Language :: Python :: 3
Classifier: Programming Language :: Python :: 3.9
Classifier: Topic :: Database
Classifier: Topic :: Software Development :: Libraries :: Python Modules
Requires-Python: >=3.9
License-File: LICENSE
License-File: NOTICE
Requires-Dist: click>=8.1.7
Requires-Dist: prompt-toolkit>=3.0.43
Requires-Dist: pygments>=2.15.1
Requires-Dist: rich>=13.7.0
Requires-Dist: pydantic>=2.6.1
Requires-Dist: boto3>=1.34.34
Requires-Dist: gremlinpython>=3.7.1
Requires-Dist: neo4j>=5.14.1
Requires-Dist: requests>=2.31.0
Requires-Dist: rdflib>=7.1.3
Requires-Dist: pyyaml>=6.0.2
Dynamic: license-file
